Alex/__init__.py
Alex/alex.py
alex_py-1.0.0.dist-info/DESCRIPTION.rst
alex_py-1.0.0.dist-info/METADATA
alex_py-1.0.0.dist-info/RECORD
alex_py-1.0.0.dist-info/WHEEL
alex_py-1.0.0.dist-info/entry_points.txt
alex_py-1.0.0.dist-info/metadata.json
alex_py-1.0.0.dist-info/top_level.txt
