Metadata-Version: 2.0
Name: alex-py
Version: 1.0.0
Summary: Alex executes your python scripts with test cases embedded
Home-page: http://github.com/kaushik94/alex
Author: Kaushik Varanasi, 
Author-email: kaushik.varanasi1@gmail.com
License: MIT
Keywords: Python,Competetive Programming,Test cases,command line,cli
Platform: UNKNOWN
Requires-Dist: docopt (>=0.6.1)
